siray/__init__.py
siray/base_client.py
siray/client.py
siray/exceptions.py
siray/models.py
siray/resources/__init__.py
siray/resources/image.py
siray/resources/video.py
siray-0.2.2.dist-info/licenses/LICENSE
siray-0.2.2.dist-info/METADATA
siray-0.2.2.dist-info/WHEEL
siray-0.2.2.dist-info/top_level.txt
siray-0.2.2.dist-info/RECORD
