Metadata-Version: 2.4
Name: siray
Version: 0.2.2
Summary: Python client library for Siray AI API
Home-page: https://github.com/siray-ai/siray-python
Author: Siray AI
Author-email: Siray AI <support@siray.ai>
License: MIT
Project-URL: Homepage, https://siray.ai
Project-URL: Documentation, https://docs.siray.ai
Project-URL: Repository, https://github.com/siray-ai/siray-python
Project-URL: Issues, https://github.com/siray-ai/siray-python/issues
Keywords: siray,ai,image-generation,video-generation,api-client
Classifier: Development Status :: 3 - Alpha
Classifier: Intended Audience :: Developers
Classifier: License :: OSI Approved :: MIT License
Classifier: Programming Language :: Python :: 3
Classifier: Programming Language :: Python :: 3.7
Classifier: Programming Language :: Python :: 3.8
Classifier: Programming Language :: Python :: 3.9
Classifier: Programming Language :: Python :: 3.10
Classifier: Programming Language :: Python :: 3.11
Classifier: Programming Language :: Python :: 3.12
Classifier: Topic :: Software Development :: Libraries :: Python Modules
Requires-Python: >=3.7
License-File: LICENSE
Requires-Dist: httpx>=0.24.0
Requires-Dist: requests>=2.28.0
Provides-Extra: dev
Requires-Dist: pytest>=7.0.0; extra == "dev"
Requires-Dist: pytest-cov>=4.0.0; extra == "dev"
Requires-Dist: black>=23.0.0; extra == "dev"
Requires-Dist: flake8>=6.0.0; extra == "dev"
Requires-Dist: mypy>=1.0.0; extra == "dev"
Requires-Dist: isort>=5.12.0; extra == "dev"
Dynamic: author
Dynamic: home-page
Dynamic: license-file
Dynamic: requires-python
